[
  {
    "serviceCode": "SC01",
    "serviceName": "Smart Pay",
    "intermediateAccount": "242588789",
    "productCode": "PRLS",
    "requiresAdditionalRegistration": false,
    "merchantCode": "MRC-SC01"
  },
  {
    "serviceCode": "SC03",
    "serviceName": "H2H_Supplier",
    "intermediateAccount": "441589789",
    "productCode": "SLPM",
    "requiresAdditionalRegistration": false,
    "merchantCode": null
  },
  {
    "serviceCode": "SC04",
    "serviceName": "Pay Advance",
    "intermediateAccount": "789852546",
    "productCode": "PAWL",
    "requiresAdditionalRegistration": true,
    "showRegistrationButton": true,
    "merchantCode": "MRC-SC04",
    "additionalRegistrationFields": [
      {
        "field": "organizationName",
        "label": "Organization Name",
        "type": "string",
        "required": true,
        "autoPopulate": "clientName",
        "readOnly": true
      },
      {
        "field": "ownerPhone",
        "label": "Owner Phone",
        "type": "string",
        "required": true,
        "autoPopulate": "ownerPhone",
        "readOnly": true
      },
      {
        "field": "ownerNrc",
        "label": "Owner NRC",
        "type": "string",
        "required": false,
        "autoPopulate": "{ownerIdType} {ownerIdValue}",
        "readOnly": true
      },
      {
        "field": "merchantCode",
        "label": "Merchant Code",
        "type": "string",
        "required": false,
        "autoPopulate": "service.merchantCode"
      }
    ],
    "requireDocumentUpload": true
  }
]
